setup.py
mzbench_api_client/__init__.py
mzbench_api_client/bdl_utils.py
mzbench_api_client/color_terminal.py
mzbench_api_client/erl_utils.py
mzbench_api_client/multipart.py
mzbench_api_client/mzbench.py
mzbench_api_client/mzbench_api_client.py
mzbench_api_client/util.py
mzbench_api_client.egg-info/PKG-INFO
mzbench_api_client.egg-info/SOURCES.txt
mzbench_api_client.egg-info/dependency_links.txt
mzbench_api_client.egg-info/entry_points.txt
mzbench_api_client.egg-info/requires.txt
mzbench_api_client.egg-info/top_level.txt